cnncam/__init__.py
cnncam/src/__init__.py
cnncam/src/cnncam.py
cnncam-1.0.0.dist-info/LICENSE
cnncam-1.0.0.dist-info/METADATA
cnncam-1.0.0.dist-info/WHEEL
cnncam-1.0.0.dist-info/top_level.txt
cnncam-1.0.0.dist-info/RECORD
