Metadata-Version: 2.1
Name: cnncam
Version: 1.0.0
Summary: Gradient Based Class Activation Maps for TensorFlow models.
License-File: LICENSE
Requires-Dist: tensorflow >=2.0.0
Requires-Dist: keras >=2.12.0
Requires-Dist: numpy >=1.23
Requires-Dist: opencv-python >=4.7.0
Requires-Dist: matplotlib >=3.7.0
Provides-Extra: dev
Requires-Dist: twine >=4.0.2 ; extra == 'dev'
